vinayvisual/__init__.py
vinayvisual/main.py
vinayvisual-2.0.dist-info/METADATA
vinayvisual-2.0.dist-info/WHEEL
vinayvisual-2.0.dist-info/top_level.txt
vinayvisual-2.0.dist-info/RECORD
