Metadata-Version: 2.1
Name: vinayvisual
Version: 2.0
Home-page: https://github.com/vinaychouhan24/vinayvisual
Author: vinaychouhan
Requires-Dist: numpy
Requires-Dist: opencv-python
Requires-Dist: scipy
